aliyunsdkdrds/__init__.py
aliyunsdkdrds/endpoint.py
aliyunsdkdrds/request/__init__.py
aliyunsdkdrds/request/v20190123/ChangeAccountPasswordRequest.py
aliyunsdkdrds/request/v20190123/ChangeInstanceAzoneRequest.py
aliyunsdkdrds/request/v20190123/CheckDrdsDbNameRequest.py
aliyunsdkdrds/request/v20190123/CheckExpandStatusRequest.py
aliyunsdkdrds/request/v20190123/CheckSqlAuditEnableStatusRequest.py
aliyunsdkdrds/request/v20190123/CreateDrdsDBRequest.py
aliyunsdkdrds/request/v20190123/CreateDrdsInstanceRequest.py
aliyunsdkdrds/request/v20190123/CreateInstanceAccountRequest.py
aliyunsdkdrds/request/v20190123/CreateInstanceInternetAddressRequest.py
aliyunsdkdrds/request/v20190123/CreateOrderForRdsRequest.py
aliyunsdkdrds/request/v20190123/CreateShardTaskRequest.py
aliyunsdkdrds/request/v20190123/DescribeBackMenuRequest.py
aliyunsdkdrds/request/v20190123/DescribeBackupDbsRequest.py
aliyunsdkdrds/request/v20190123/DescribeBackupLocalRequest.py
aliyunsdkdrds/request/v20190123/DescribeBackupPolicyRequest.py
aliyunsdkdrds/request/v20190123/DescribeBackupSetsRequest.py
aliyunsdkdrds/request/v20190123/DescribeBackupTimesRequest.py
aliyunsdkdrds/request/v20190123/DescribeBroadcastTablesRequest.py
aliyunsdkdrds/request/v20190123/DescribeDbInstanceDbsRequest.py
aliyunsdkdrds/request/v20190123/DescribeDbInstancesRequest.py
aliyunsdkdrds/request/v20190123/DescribeDrdsDBClusterRequest.py
aliyunsdkdrds/request/v20190123/DescribeDrdsDBIpWhiteListRequest.py
aliyunsdkdrds/request/v20190123/DescribeDrdsDBRequest.py
aliyunsdkdrds/request/v20190123/DescribeDrdsDBsRequest.py
aliyunsdkdrds/request/v20190123/DescribeDrdsDbInstanceRequest.py
aliyunsdkdrds/request/v20190123/DescribeDrdsDbInstancesRequest.py
aliyunsdkdrds/request/v20190123/DescribeDrdsDbRdsNameListRequest.py
aliyunsdkdrds/request/v20190123/DescribeDrdsInstanceDbMonitorRequest.py
aliyunsdkdrds/request/v20190123/DescribeDrdsInstanceLevelTasksRequest.py
aliyunsdkdrds/request/v20190123/DescribeDrdsInstanceMonitorRequest.py
aliyun_python_sdk_drds-20210523.0.2.dist-info/LICENSE
aliyun_python_sdk_drds-20210523.0.2.dist-info/METADATA
aliyun_python_sdk_drds-20210523.0.2.dist-info/WHEEL
aliyun_python_sdk_drds-20210523.0.2.dist-info/top_level.txt
aliyun_python_sdk_drds-20210523.0.2.dist-info/RECORD
